SpringBootKuangjiaRumenjiaochengCYuyanBianchengWang/README.md
SpringBootKuangjiaRumenjiaochengCYuyanBianchengWang/__init__.py
SpringBootKuangjiaRumenjiaochengCYuyanBianchengWang/__main__.py
SpringBootKuangjiaRumenjiaochengCYuyanBianchengWang/file.epub
SpringBootKuangjiaRumenjiaochengCYuyanBianchengWang/index.html
SpringBootKuangjiaRumenjiaochengCYuyanBianchengWang/css/__init__.py
SpringBootKuangjiaRumenjiaochengCYuyanBianchengWang/css/annotations.css
SpringBootKuangjiaRumenjiaochengCYuyanBianchengWang/css/main.css
SpringBootKuangjiaRumenjiaochengCYuyanBianchengWang/css/normalize.css
SpringBootKuangjiaRumenjiaochengCYuyanBianchengWang/css/popup.css
SpringBootKuangjiaRumenjiaochengCYuyanBianchengWang/font/__init__.py
SpringBootKuangjiaRumenjiaochengCYuyanBianchengWang/font/fontello.eot
SpringBootKuangjiaRumenjiaochengCYuyanBianchengWang/font/fontello.svg
SpringBootKuangjiaRumenjiaochengCYuyanBianchengWang/font/fontello.ttf
SpringBootKuangjiaRumenjiaochengCYuyanBianchengWang/font/fontello.woff
SpringBootKuangjiaRumenjiaochengCYuyanBianchengWang/img/__init__.py
SpringBootKuangjiaRumenjiaochengCYuyanBianchengWang/img/annotator-glyph-sprite.png
SpringBootKuangjiaRumenjiaochengCYuyanBianchengWang/img/annotator-icon-sprite.png
SpringBootKuangjiaRumenjiaochengCYuyanBianchengWang/img/apple-touch-icon.png
SpringBootKuangjiaRumenjiaochengCYuyanBianchengWang/img/cancelfullscreen.png
SpringBootKuangjiaRumenjiaochengCYuyanBianchengWang/img/close.png
SpringBootKuangjiaRumenjiaochengCYuyanBianchengWang/img/fullscreen.png
SpringBootKuangjiaRumenjiaochengCYuyanBianchengWang/img/loader.gif
SpringBootKuangjiaRumenjiaochengCYuyanBianchengWang/img/menu-icon.png
SpringBootKuangjiaRumenjiaochengCYuyanBianchengWang/img/save.png
SpringBootKuangjiaRumenjiaochengCYuyanBianchengWang/img/saved.png
SpringBootKuangjiaRumenjiaochengCYuyanBianchengWang/img/settings-s.png
SpringBootKuangjiaRumenjiaochengCYuyanBianchengWang/img/settings.png
spring_boot_kuangjia_rumenjiaocheng_c_yuyan_biancheng_wang-2024.3.5.0.dist-info/METADATA
spring_boot_kuangjia_rumenjiaocheng_c_yuyan_biancheng_wang-2024.3.5.0.dist-info/WHEEL
spring_boot_kuangjia_rumenjiaocheng_c_yuyan_biancheng_wang-2024.3.5.0.dist-info/entry_points.txt
spring_boot_kuangjia_rumenjiaocheng_c_yuyan_biancheng_wang-2024.3.5.0.dist-info/top_level.txt
spring_boot_kuangjia_rumenjiaocheng_c_yuyan_biancheng_wang-2024.3.5.0.dist-info/RECORD
